{"cameraMode":{"drawMode":0,"name":"Shaded","section":"Shading Mode"},"sceneLighting":true,"audioPlay":false,"sceneViewState":{"m_AlwaysRefresh":false,"showFog":true,"showSkybox":true,"showFlares":true,"showImageEffects":true,"showParticleSystems":true,"showVisualEffectGraphs":true,"m_FxEnabled":true},"in2DMode":false,"pivot":{"x":2.485666275024414,"y":2.5068719387054445,"z":-8.1431303024292},"rotation":{"x":0.01656603254377842,"y":-0.16308030486106873,"z":0.002893366850912571,"w":0.9866037368774414},"size":0.428153932094574,"orthographic":false}